django_synth/loaders.py
django_synth/template.py
django_synth/__init__.py
django_synth-0.7.6.dist-info/DESCRIPTION.rst
django_synth-0.7.6.dist-info/METADATA
django_synth-0.7.6.dist-info/metadata.json
django_synth-0.7.6.dist-info/RECORD
django_synth-0.7.6.dist-info/top_level.txt
django_synth-0.7.6.dist-info/WHEEL
django_synth-0.7.6.dist-info/zip-safe
