Metadata-Version: 2.0
Name: django-synth
Version: 0.7.6
Summary: A Simple Integration Between Django and Synth
Home-page: https://github.com/ajg/django-synth
Author: Alvaro J. Genial
Author-email: genial@alva.ro
License: BSD
Keywords: django,tmpl,ssi,template,framework
Platform: UNKNOWN
Classifier: Development Status :: 4 - Beta
Classifier: Environment :: Console
Classifier: Framework :: Django
Classifier: Intended Audience :: Developers
Classifier: Intended Audience :: Other Audience
Classifier: Intended Audience :: Science/Research
Classifier: License :: OSI Approved :: BSD License
Classifier: Natural Language :: English
Classifier: Operating System :: OS Independent
Classifier: Programming Language :: C++
Classifier: Programming Language :: Python
Classifier: Programming Language :: Python :: 2
Classifier: Programming Language :: Python :: 2.7
Classifier: Programming Language :: Python :: 3
Classifier: Programming Language :: Python :: 3.4
Classifier: Topic :: Internet :: WWW/HTTP
Classifier: Topic :: Software Development :: Libraries
Classifier: Topic :: Scientific/Engineering
Requires-Dist: synth (>=1.0.8)
Requires-Dist: django (>=1.5)
